enforce_with/__init__.py
enforce_with/enforce_with.py
enforce_with-1.1.0.dist-info/METADATA
enforce_with-1.1.0.dist-info/WHEEL
enforce_with-1.1.0.dist-info/RECORD
