Metadata-Version: 2.4
Name: enforce-with
Version: 1.1.0
Summary: Enforce the usage of with keyword
Project-URL: Homepage, https://github.com/pyhacks/enforce-with
Author-email: pyhacks <enginyildirim111@gmail.com>
Keywords: enforce,with
Requires-Dist: access-specifiers
